{
  "updated": "2026-07-15T12:48:39Z",
  "quotes": {
    "AMD": {
      "price": 534.39,
      "rsi10": 51.48,
      "rsi_prev": 57.5,
      "rsiW": 71.85,
      "ema200": 320.76,
      "emaTrend": "subiendo",
      "emaSlope": 16.213,
      "bb_lo": 496.05,
      "bb_hi": 570.45,
      "bb_recov": false,
      "bb_below": false,
      "bb_above": false,
      "bb_squeeze": true,
      "bb_near_lo": false,
      "poc_proxy": 168.18,
      "div_bullish": false,
      "price_prev": 557.8900146484375,
      "bb_lo_prev": 488.95,
      "rsi_bounced_15": false,
      "rsiHistory": [
        60.67,
        63.21,
        54.49,
        54.46,
        57.39,
        54.08,
        58.42,
        66.55,
        55.0,
        49.5,
        56.65,
        48.62,
        48.91,
        55.26,
        57.5
      ]
    },
    "AMZN": {
      "price": 247.31,
      "rsi10": 56.26,
      "rsi_prev": 53.44,
      "rsiW": 52.22,
      "ema200": 234.92,
      "emaTrend": "lateral",
      "emaSlope": 0.518,
      "bb_lo": 229.1,
      "bb_hi": 251.86,
      "bb_recov": false,
      "bb_below": false,
      "bb_above": false,
      "bb_squeeze": false,
      "bb_near_lo": false,
      "poc_proxy": 228.61,
      "div_bullish": false,
      "price_prev": 245.33999633789062,
      "bb_lo_prev": 229.24,
      "rsi_bounced_15": false,
      "rsiHistory": [
        43.89,
        34.24,
        36.02,
        36.25,
        30.64,
        38.86,
        47.87,
        46.05,
        49.99,
        51.14,
        52.98,
        55.26,
        51.65,
        56.25,
        53.44
      ]
    },
    "BABA": {
      "price": 112.32,
      "rsi10": 64.09,
      "rsi_prev": 64.19,
      "rsiW": 40.84,
      "ema200": 131.67,
      "emaTrend": "bajando",
      "emaSlope": -4.309,
      "bb_lo": 90.17,
      "bb_hi": 117.24,
      "bb_recov": false,
      "bb_below": false,
      "bb_above": false,
      "bb_squeeze": true,
      "bb_near_lo": false,
      "poc_proxy": 109.03,
      "div_bullish": false,
      "price_prev": 112.3499984741211,
      "bb_lo_prev": 90.13,
      "rsi_bounced_15": false,
      "rsiHistory": [
        16.6,
        14.73,
        12.83,
        10.32,
        10.2,
        13.26,
        15.4,
        24.3,
        21.94,
        29.25,
        30.19,
        58.9,
        62.32,
        64.16,
        64.19
      ]
    },
    "BNB": {
      "price": 578.88,
      "rsi10": 53.18,
      "rsi_prev": 55.51,
      "rsiW": 42.87,
      "ema200": 665.09,
      "emaTrend": "bajando",
      "emaSlope": -2.928,
      "bb_lo": 545.16,
      "bb_hi": 592.23,
      "bb_recov": false,
      "bb_below": false,
      "bb_above": false,
      "bb_squeeze": false,
      "bb_near_lo": false,
      "poc_proxy": 627.54,
      "div_bullish": false,
      "price_prev": 581.7556762695312,
      "bb_lo_prev": 544.39,
      "rsi_bounced_15": false,
      "rsiHistory": [
        31.31,
        34.72,
        40.58,
        50.26,
        51.14,
        58.55,
        56.18,
        50.56,
        45.58,
        45.69,
        50.35,
        50.24,
        49.49,
        43.84,
        55.51
      ]
    },
    "BRK.B": {
      "price": 496.85,
      "rsi10": 52.38,
      "rsi_prev": 47.84,
      "rsiW": 65.31,
      "ema200": 487.4,
      "emaTrend": "lateral",
      "emaSlope": 0.388,
      "bb_lo": 484.91,
      "bb_hi": 506.94,
      "bb_recov": false,
      "bb_below": false,
      "bb_above": false,
      "bb_squeeze": true,
      "bb_near_lo": false,
      "poc_proxy": 527.98,
      "div_bullish": false,
      "price_prev": 493.7099914550781,
      "bb_lo_prev": 483.52,
      "rsi_bounced_15": false,
      "rsiHistory": [
        56.8,
        55.29,
        61.38,
        64.02,
        50.57,
        63.7,
        59.4,
        63.87,
        62.74,
        70.06,
        67.85,
        63.09,
        49.37,
        50.23,
        47.84
      ]
    },
    "BTC": {
      "price": 64833.54,
      "rsi10": 59.54,
      "rsi_prev": 60.34,
      "rsiW": 43.41,
      "ema200": 74478.83,
      "emaTrend": "bajando",
      "emaSlope": -3.264,
      "bb_lo": 58494.02,
      "bb_hi": 66037.47,
      "bb_recov": false,
      "bb_below": false,
      "bb_above": false,
      "bb_squeeze": false,
      "bb_near_lo": false,
      "poc_proxy": 67342.69,
      "div_bullish": false,
      "price_prev": 64956.11328125,
      "bb_lo_prev": 58276.47,
      "rsi_bounced_15": false,
      "rsiHistory": [
        28.09,
        38.74,
        47.58,
        52.97,
        55.58,
        57.78,
        59.92,
        55.07,
        48.57,
        54.0,
        58.83,
        56.53,
        56.2,
        45.93,
        60.34
      ]
    },
    "DIA": {
      "price": 524.47,
      "rsi10": 57.54,
      "rsi_prev": 60.71,
      "rsiW": 79.32,
      "ema200": 486.49,
      "emaTrend": "subiendo",
      "emaSlope": 1.543,
      "bb_lo": 512.11,
      "bb_hi": 530.3,
      "bb_recov": false,
      "bb_below": false,
      "bb_above": false,
      "bb_squeeze": true,
      "bb_near_lo": false,
      "poc_proxy": 501.08,
      "div_bullish": false,
      "price_prev": 525.780029296875,
      "bb_lo_prev": 510.14,
      "rsi_bounced_15": false,
      "rsiHistory": [
        57.32,
        59.12,
        58.32,
        60.77,
        61.74,
        58.45,
        64.0,
        64.94,
        64.95,
        71.93,
        74.23,
        69.54,
        55.92,
        58.19,
        60.71
      ]
    },
    "ETH": {
      "price": 1895.85,
      "rsi10": 70.65,
      "rsi_prev": 70.09,
      "rsiW": 48.36,
      "ema200": 2215.94,
      "emaTrend": "bajando",
      "emaSlope": -4.31,
      "bb_lo": 1521.26,
      "bb_hi": 1931.31,
      "bb_recov": false,
      "bb_below": false,
      "bb_above": false,
      "bb_squeeze": false,
      "bb_near_lo": false,
      "poc_proxy": 1799.54,
      "div_bullish": false,
      "price_prev": 1889.4798583984375,
      "bb_lo_prev": 1508.72,
      "rsi_bounced_15": false,
      "rsiHistory": [
        34.09,
        42.0,
        55.45,
        61.87,
        64.09,
        64.5,
        66.06,
        60.19,
        55.34,
        55.62,
        62.89,
        61.24,
        63.71,
        56.42,
        70.09
      ]
    },
    "GOOGL": {
      "price": 352.51,
      "rsi10": 41.96,
      "rsi_prev": 46.66,
      "rsiW": 58.84,
      "ema200": 317.01,
      "emaTrend": "subiendo",
      "emaSlope": 2.744,
      "bb_lo": 339.02,
      "bb_hi": 376.22,
      "bb_recov": false,
      "bb_below": false,
      "bb_above": false,
      "bb_squeeze": false,
      "bb_near_lo": false,
      "poc_proxy": 207.22,
      "div_bullish": false,
      "price_prev": 357.17999267578125,
      "bb_lo_prev": 339.43,
      "rsi_bounced_15": false,
      "rsiHistory": [
        48.59,
        35.4,
        33.45,
        32.97,
        32.02,
        28.37,
        45.99,
        49.17,
        52.38,
        51.16,
        56.78,
        57.26,
        51.6,
        48.45,
        46.66
      ]
    },
    "KO": {
      "price": 84.25,
      "rsi10": 62.02,
      "rsi_prev": 58.59,
      "rsiW": 65.38,
      "ema200": 76.13,
      "emaTrend": "subiendo",
      "emaSlope": 1.604,
      "bb_lo": 78.68,
      "bb_hi": 84.99,
      "bb_recov": false,
      "bb_below": false,
      "bb_above": false,
      "bb_squeeze": false,
      "bb_near_lo": false,
      "poc_proxy": 75.52,
      "div_bullish": false,
      "price_prev": 83.48999786376953,
      "bb_lo_prev": 78.78,
      "rsi_bounced_15": false,
      "rsiHistory": [
        44.3,
        45.24,
        50.42,
        52.28,
        50.96,
        63.54,
        63.63,
        53.15,
        53.28,
        67.07,
        59.05,
        63.53,
        59.24,
        54.4,
        58.59
      ]
    },
    "MCD": {
      "price": 272.61,
      "rsi10": 44.1,
      "rsi_prev": 47.0,
      "rsiW": 43.34,
      "ema200": 297.2,
      "emaTrend": "lateral",
      "emaSlope": -1.499,
      "bb_lo": 262.99,
      "bb_hi": 289.26,
      "bb_recov": false,
      "bb_below": false,
      "bb_above": false,
      "bb_squeeze": false,
      "bb_near_lo": false,
      "poc_proxy": 304.22,
      "div_bullish": false,
      "price_prev": 274.6000061035156,
      "bb_lo_prev": 263.18,
      "rsi_bounced_15": false,
      "rsiHistory": [
        42.93,
        31.49,
        35.02,
        39.91,
        29.52,
        39.33,
        36.54,
        42.08,
        40.96,
        57.08,
        55.38,
        58.65,
        52.41,
        49.8,
        47.0
      ]
    },
    "MELI": {
      "price": 1867.3,
      "rsi10": 76.62,
      "rsi_prev": 75.17,
      "rsiW": 53.8,
      "ema200": 1880.62,
      "emaTrend": "bajando",
      "emaSlope": -1.778,
      "bb_lo": 1526.77,
      "bb_hi": 1887.84,
      "bb_recov": false,
      "bb_below": false,
      "bb_above": false,
      "bb_squeeze": false,
      "bb_near_lo": false,
      "poc_proxy": 1778.83,
      "div_bullish": false,
      "price_prev": 1852.219970703125,
      "bb_lo_prev": 1525.01,
      "rsi_bounced_15": false,
      "rsiHistory": [
        48.3,
        41.19,
        40.35,
        53.97,
        47.56,
        55.67,
        56.73,
        58.7,
        64.35,
        66.73,
        71.04,
        71.8,
        70.7,
        70.26,
        75.17
      ]
    },
    "META": {
      "price": 661.04,
      "rsi10": 66.88,
      "rsi_prev": 66.0,
      "rsiW": 59.16,
      "ema200": 632.07,
      "emaTrend": "lateral",
      "emaSlope": -1.201,
      "bb_lo": 519.87,
      "bb_hi": 667.58,
      "bb_recov": false,
      "bb_below": false,
      "bb_above": false,
      "bb_squeeze": false,
      "bb_near_lo": false,
      "poc_proxy": 604.58,
      "div_bullish": true,
      "price_prev": 656.72998046875,
      "bb_lo_prev": 521.17,
      "rsi_bounced_15": false,
      "rsiHistory": [
        38.14,
        37.59,
        36.0,
        31.22,
        35.93,
        43.17,
        43.57,
        63.74,
        51.4,
        56.79,
        61.01,
        56.05,
        63.55,
        70.89,
        66.0
      ]
    },
    "MSFT": {
      "price": 390.99,
      "rsi10": 54.39,
      "rsi_prev": 49.42,
      "rsiW": 43.82,
      "ema200": 425.86,
      "emaTrend": "bajando",
      "emaSlope": -2.198,
      "bb_lo": 358.2,
      "bb_hi": 402.89,
      "bb_recov": false,
      "bb_below": false,
      "bb_above": false,
      "bb_squeeze": true,
      "bb_near_lo": false,
      "poc_proxy": 405.75,
      "div_bullish": false,
      "price_prev": 385.1000061035156,
      "bb_lo_prev": 358.22,
      "rsi_bounced_15": true,
      "rsiHistory": [
        30.65,
        25.86,
        32.3,
        28.73,
        24.3,
        40.56,
        38.55,
        41.79,
        49.31,
        53.03,
        50.54,
        51.94,
        47.98,
        48.79,
        49.42
      ]
    },
    "PEP": {
      "price": 138.49,
      "rsi10": 42.44,
      "rsi_prev": 39.2,
      "rsiW": 44.26,
      "ema200": 149.29,
      "emaTrend": "lateral",
      "emaSlope": -1.109,
      "bb_lo": 135.75,
      "bb_hi": 147.26,
      "bb_recov": false,
      "bb_below": false,
      "bb_above": false,
      "bb_squeeze": false,
      "bb_near_lo": false,
      "poc_proxy": 153.88,
      "div_bullish": true,
      "price_prev": 137.3800048828125,
      "bb_lo_prev": 136.11,
      "rsi_bounced_15": true,
      "rsiHistory": [
        39.47,
        35.83,
        41.91,
        42.89,
        34.71,
        42.94,
        35.7,
        29.1,
        47.89,
        54.94,
        52.54,
        56.39,
        49.83,
        40.08,
        39.2
      ]
    },
    "QQQ": {
      "price": 711.74,
      "rsi10": 45.88,
      "rsi_prev": 52.99,
      "rsiW": 59.86,
      "ema200": 643.47,
      "emaTrend": "subiendo",
      "emaSlope": 2.623,
      "bb_lo": 700.77,
      "bb_hi": 743.82,
      "bb_recov": false,
      "bb_below": false,
      "bb_above": false,
      "bb_squeeze": true,
      "bb_near_lo": true,
      "poc_proxy": 636.96,
      "div_bullish": false,
      "price_prev": 725.510009765625,
      "bb_lo_prev": 701.45,
      "rsi_bounced_15": false,
      "rsiHistory": [
        58.81,
        57.35,
        45.82,
        44.58,
        47.58,
        43.14,
        52.0,
        57.2,
        51.55,
        45.9,
        50.77,
        44.89,
        45.93,
        51.9,
        52.99
      ]
    },
    "SPY": {
      "price": 749.17,
      "rsi10": 54.16,
      "rsi_prev": 61.45,
      "rsiW": 66.2,
      "ema200": 695.13,
      "emaTrend": "subiendo",
      "emaSlope": 1.513,
      "bb_lo": 730.13,
      "bb_hi": 758.63,
      "bb_recov": false,
      "bb_below": false,
      "bb_above": false,
      "bb_squeeze": false,
      "bb_near_lo": false,
      "poc_proxy": 714.98,
      "div_bullish": false,
      "price_prev": 754.9500122070312,
      "bb_lo_prev": 729.46,
      "rsi_bounced_15": false,
      "rsiHistory": [
        52.84,
        50.79,
        42.39,
        42.15,
        43.28,
        39.04,
        51.08,
        55.75,
        54.73,
        53.68,
        59.44,
        55.25,
        52.58,
        58.64,
        61.45
      ]
    },
    "TSLA": {
      "price": 394.76,
      "rsi10": 46.34,
      "rsi_prev": 51.84,
      "rsiW": 48.74,
      "ema200": 397.54,
      "emaTrend": "lateral",
      "emaSlope": 0.155,
      "bb_lo": 372.38,
      "bb_hi": 428.93,
      "bb_recov": false,
      "bb_below": false,
      "bb_above": false,
      "bb_squeeze": false,
      "bb_near_lo": false,
      "poc_proxy": 348.02,
      "div_bullish": false,
      "price_prev": 407.760009765625,
      "bb_lo_prev": 372.72,
      "rsi_bounced_15": false,
      "rsiHistory": [
        45.92,
        48.67,
        37.73,
        35.43,
        35.27,
        38.73,
        56.72,
        60.26,
        62.1,
        46.01,
        56.39,
        49.6,
        46.35,
        51.35,
        51.84
      ]
    },
    "V": {
      "price": 357.75,
      "rsi10": 68.46,
      "rsi_prev": 60.63,
      "rsiW": 68.38,
      "ema200": 328.03,
      "emaTrend": "lateral",
      "emaSlope": 0.869,
      "bb_lo": 315.79,
      "bb_hi": 364.3,
      "bb_recov": false,
      "bb_below": false,
      "bb_above": false,
      "bb_squeeze": false,
      "bb_near_lo": false,
      "poc_proxy": 339.85,
      "div_bullish": false,
      "price_prev": 348.9700012207031,
      "bb_lo_prev": 313.64,
      "rsi_bounced_15": false,
      "rsiHistory": [
        53.91,
        52.93,
        55.57,
        60.49,
        57.27,
        64.31,
        69.59,
        70.86,
        76.83,
        82.38,
        73.72,
        65.76,
        59.2,
        59.84,
        60.63
      ]
    },
    "WMT": {
      "price": 114.78,
      "rsi10": 49.54,
      "rsi_prev": 46.33,
      "rsiW": 35.79,
      "ema200": 116.42,
      "emaTrend": "lateral",
      "emaSlope": -0.244,
      "bb_lo": 108.39,
      "bb_hi": 122.61,
      "bb_recov": false,
      "bb_below": false,
      "bb_above": false,
      "bb_squeeze": false,
      "bb_near_lo": false,
      "poc_proxy": 108.56,
      "div_bullish": true,
      "price_prev": 113.9000015258789,
      "bb_lo_prev": 108.36,
      "rsi_bounced_15": true,
      "rsiHistory": [
        36.58,
        36.58,
        47.63,
        45.96,
        35.4,
        35.15,
        32.09,
        28.68,
        20.61,
        34.53,
        32.07,
        35.87,
        42.16,
        39.69,
        46.33
      ]
    },
    "GLD": {
      "price": 367.13,
      "rsi10": 35.91,
      "rsi_prev": 45.11,
      "rsiW": 33.01,
      "ema200": 396.52,
      "emaTrend": "lateral",
      "emaSlope": -0.98,
      "bb_lo": 360.25,
      "bb_hi": 396.7,
      "bb_recov": false,
      "bb_below": false,
      "bb_above": false,
      "bb_squeeze": false,
      "bb_near_lo": true,
      "poc_proxy": 346.1,
      "div_bullish": true,
      "price_prev": 377.010009765625,
      "bb_lo_prev": 361.68,
      "rsi_bounced_15": false,
      "rsiHistory": [
        37.97,
        36.16,
        31.38,
        25.51,
        30.03,
        35.17,
        32.01,
        31.88,
        35.04,
        44.71,
        49.18,
        44.54,
        41.68,
        46.37,
        45.11
      ]
    },
    "NU": {
      "price": 13.99,
      "rsi10": 65.47,
      "rsi_prev": 60.14,
      "rsiW": 50.54,
      "ema200": 14.31,
      "emaTrend": "bajando",
      "emaSlope": -1.518,
      "bb_lo": 12.16,
      "bb_hi": 14.23,
      "bb_recov": false,
      "bb_below": false,
      "bb_above": false,
      "bb_squeeze": true,
      "bb_near_lo": false,
      "poc_proxy": 13.34,
      "div_bullish": false,
      "price_prev": 13.670000076293945,
      "bb_lo_prev": 12.05,
      "rsi_bounced_15": false,
      "rsiHistory": [
        55.49,
        50.96,
        48.13,
        48.13,
        62.28,
        61.23,
        64.99,
        65.47,
        68.97,
        74.78,
        61.9,
        56.17,
        61.17,
        62.59,
        60.14
      ]
    },
    "NVDA": {
      "price": 203.53,
      "rsi10": 51.05,
      "rsi_prev": 61.67,
      "rsiW": 48.01,
      "ema200": 190.11,
      "emaTrend": "lateral",
      "emaSlope": 1.283,
      "bb_lo": 190.09,
      "bb_hi": 213.68,
      "bb_recov": false,
      "bb_below": false,
      "bb_above": false,
      "bb_squeeze": false,
      "bb_near_lo": false,
      "poc_proxy": 188.68,
      "div_bullish": false,
      "price_prev": 210.9600067138672,
      "bb_lo_prev": 190.1,
      "rsi_bounced_15": false,
      "rsiHistory": [
        50.47,
        48.18,
        39.72,
        38.81,
        35.93,
        33.23,
        37.21,
        44.88,
        42.08,
        39.11,
        40.34,
        42.79,
        53.78,
        51.72,
        61.67
      ]
    },
    "AAPL": {
      "price": 317.31,
      "rsi10": 67.62,
      "rsi_prev": 66.02,
      "rsiW": 63.5,
      "ema200": 271.96,
      "emaTrend": "subiendo",
      "emaSlope": 2.207,
      "bb_lo": 275.22,
      "bb_hi": 323.16,
      "bb_recov": false,
      "bb_below": false,
      "bb_above": false,
      "bb_squeeze": false,
      "bb_near_lo": false,
      "poc_proxy": 232.74,
      "div_bullish": false,
      "price_prev": 315.32000732421875,
      "bb_lo_prev": 275.59,
      "rsi_bounced_15": true,
      "rsiHistory": [
        48.96,
        47.55,
        43.76,
        42.08,
        25.87,
        38.53,
        36.88,
        46.42,
        51.76,
        63.3,
        65.87,
        63.42,
        65.37,
        67.37,
        66.02
      ]
    },
    "INTC": {
      "price": 103.12,
      "rsi10": 34.08,
      "rsi_prev": 39.03,
      "rsiW": 58.37,
      "ema200": 72.18,
      "emaTrend": "subiendo",
      "emaSlope": 17.463,
      "bb_lo": 103.12,
      "bb_hi": 144.64,
      "bb_recov": false,
      "bb_below": false,
      "bb_above": false,
      "bb_squeeze": false,
      "bb_near_lo": true,
      "poc_proxy": 22.21,
      "div_bullish": false,
      "price_prev": 109.83999633789062,
      "bb_lo_prev": 105.8,
      "rsi_bounced_15": false,
      "rsiHistory": [
        65.7,
        69.49,
        60.27,
        59.63,
        60.53,
        55.41,
        58.34,
        64.38,
        51.22,
        45.72,
        47.46,
        38.68,
        38.58,
        41.19,
        39.03
      ]
    }
  },
  "cycles": {
    "WMT": {
      "is_silenced": true,
      "rsi_hit_50": true,
      "rsi_reset": false,
      "posicion": "completa",
      "override_sent": false
    },
    "PEP": {
      "is_silenced": false,
      "rsi_hit_50": false,
      "rsi_reset": false,
      "override_sent": false
    },
    "GLD": {
      "is_silenced": true,
      "rsi_hit_50": false,
      "rsi_reset": false,
      "posicion": "completa",
      "override_sent": true
    },
    "GOOGL": {
      "is_silenced": false,
      "rsi_hit_50": false,
      "rsi_reset": false,
      "override_sent": false
    },
    "AMZN": {
      "is_silenced": true,
      "rsi_hit_50": true,
      "rsi_reset": false,
      "posicion": "completa",
      "override_sent": false
    },
    "MCD": {
      "is_silenced": false,
      "rsi_hit_50": false,
      "rsi_reset": false,
      "override_sent": false
    }
  },
  "daily": {
    "date": "2026-07-14",
    "signals": [],
    "watchlist": [
      "PEP"
    ],
    "entradas": []
  }
}