{
  "updated": "2026-06-07T12:56:26Z",
  "quotes": {
    "AMD": {
      "price": 466.38,
      "rsi10": 48.87,
      "rsi_prev": 69.13,
      "rsiW": 75.03,
      "ema200": 265.29,
      "emaTrend": "subiendo",
      "emaSlope": 19.993,
      "bb_lo": 398.18,
      "bb_hi": 549.69,
      "bb_recov": false,
      "bb_below": false,
      "bb_above": false,
      "bb_squeeze": true,
      "bb_near_lo": false,
      "poc_proxy": 133.04,
      "div_bullish": false,
      "price_prev": 523.2000122070312,
      "bb_lo_prev": 390.1,
      "rsi_bounced_15": false,
      "rsiHistory": [
        76.57,
        64.35,
        62.99,
        59.86,
        68.31,
        68.75,
        72.52,
        78.39,
        74.34,
        77.79,
        76.78,
        73.59,
        75.73,
        79.18,
        69.13
      ],
      "rsi_direction": "bajando",
      "promoted_by_div": false
    },
    "AMZN": {
      "price": 246.03,
      "rsi10": 32.21,
      "rsi_prev": 38.84,
      "rsiW": 51.05,
      "ema200": 233.14,
      "emaTrend": "subiendo",
      "emaSlope": 2.795,
      "bb_lo": 249.33,
      "bb_hi": 278.91,
      "bb_recov": false,
      "bb_below": true,
      "bb_above": false,
      "bb_squeeze": false,
      "bb_near_lo": false,
      "poc_proxy": 228.61,
      "div_bullish": false,
      "price_prev": 253.7899932861328,
      "bb_lo_prev": 252.85,
      "rsi_bounced_15": false,
      "rsiHistory": [
        58.96,
        53.13,
        54.31,
        44.77,
        53.99,
        58.66,
        54.82,
        52.97,
        62.04,
        64.53,
        57.93,
        43.98,
        38.74,
        32.79,
        38.84
      ],
      "rsi_direction": "bajando",
      "promoted_by_div": false
    },
    "BABA": {
      "price": 121.06,
      "rsi10": 33.73,
      "rsi_prev": 40.7,
      "rsiW": 34.79,
      "ema200": 138.95,
      "emaTrend": "lateral",
      "emaSlope": -1.182,
      "bb_lo": 119.55,
      "bb_hi": 143.91,
      "bb_recov": false,
      "bb_below": false,
      "bb_above": false,
      "bb_squeeze": false,
      "bb_near_lo": true,
      "poc_proxy": 119.4,
      "div_bullish": false,
      "price_prev": 125.94999694824219,
      "bb_lo_prev": 120.94,
      "rsi_bounced_15": false,
      "rsiHistory": [
        57.55,
        45.09,
        46.11,
        49.78,
        47.99,
        43.54,
        41.45,
        40.66,
        38.08,
        35.72,
        32.97,
        36.29,
        49.13,
        42.75,
        40.7
      ],
      "rsi_direction": "bajando",
      "promoted_by_div": false
    },
    "BNB": {
      "price": 588.53,
      "rsi10": 35.47,
      "rsi_prev": 29.7,
      "rsiW": 35.76,
      "ema200": 704.95,
      "emaTrend": "bajando",
      "emaSlope": -1.8,
      "bb_lo": 568.74,
      "bb_hi": 719.32,
      "bb_recov": true,
      "bb_below": false,
      "bb_above": false,
      "bb_squeeze": false,
      "bb_near_lo": false,
      "poc_proxy": 657.92,
      "div_bullish": false,
      "price_prev": 574.5108032226562,
      "bb_lo_prev": 575.88,
      "rsi_bounced_15": true,
      "rsiHistory": [
        54.27,
        54.53,
        58.74,
        52.86,
        47.05,
        40.05,
        44.2,
        74.79,
        69.56,
        61.18,
        45.69,
        37.92,
        34.38,
        28.72,
        29.7
      ],
      "rsi_direction": "subiendo",
      "promoted_by_div": false
    },
    "BRK.B": {
      "price": 488.13,
      "rsi10": 63.78,
      "rsi_prev": 51.74,
      "rsiW": 53.99,
      "ema200": 485.48,
      "emaTrend": "lateral",
      "emaSlope": -0.214,
      "bb_lo": 470.31,
      "bb_hi": 490.51,
      "bb_recov": false,
      "bb_below": false,
      "bb_above": false,
      "bb_squeeze": true,
      "bb_near_lo": false,
      "poc_proxy": 527.98,
      "div_bullish": false,
      "price_prev": 478.6300048828125,
      "bb_lo_prev": 470.06,
      "rsi_bounced_15": false,
      "rsiHistory": [
        63.72,
        60.53,
        67.97,
        52.61,
        53.26,
        51.62,
        60.96,
        55.8,
        49.55,
        45.7,
        41.49,
        36.22,
        38.74,
        46.21,
        51.74
      ],
      "rsi_direction": "subiendo",
      "promoted_by_div": false
    },
    "BTC": {
      "price": 61805.37,
      "rsi10": 16.4,
      "rsi_prev": 9.77,
      "rsiW": 27.31,
      "ema200": 79885.2,
      "emaTrend": "bajando",
      "emaSlope": -2.268,
      "bb_lo": 59713.34,
      "bb_hi": 83488.59,
      "bb_recov": true,
      "bb_below": false,
      "bb_above": false,
      "bb_squeeze": false,
      "bb_near_lo": false,
      "poc_proxy": 69997.53,
      "div_bullish": false,
      "price_prev": 60867.4140625,
      "bb_lo_prev": 61152.99,
      "rsi_bounced_15": false,
      "rsiHistory": [
        42.53,
        44.5,
        46.47,
        38.96,
        32.94,
        30.12,
        29.55,
        32.85,
        32.08,
        24.06,
        15.35,
        12.43,
        12.23,
        9.81,
        9.77
      ],
      "rsi_direction": "subiendo",
      "promoted_by_div": false
    },
    "DIA": {
      "price": 509.7,
      "rsi10": 56.9,
      "rsi_prev": 70.13,
      "rsiW": 69.4,
      "ema200": 477.25,
      "emaTrend": "lateral",
      "emaSlope": 1.208,
      "bb_lo": 490.49,
      "bb_hi": 517.01,
      "bb_recov": false,
      "bb_below": false,
      "bb_above": false,
      "bb_squeeze": false,
      "bb_near_lo": false,
      "poc_proxy": 485.02,
      "div_bullish": false,
      "price_prev": 516.7000122070312,
      "bb_lo_prev": 489.67,
      "rsi_bounced_15": false,
      "rsiHistory": [
        66.05,
        53.7,
        56.43,
        50.33,
        60.21,
        63.87,
        67.37,
        65.34,
        67.38,
        67.6,
        72.21,
        72.97,
        75.85,
        60.05,
        70.13
      ],
      "rsi_direction": "bajando",
      "promoted_by_div": false
    },
    "ETH": {
      "price": 1616.41,
      "rsi10": 16.98,
      "rsi_prev": 7.82,
      "rsiW": 21.69,
      "ema200": 2447.73,
      "emaTrend": "bajando",
      "emaSlope": -4.177,
      "bb_lo": 1589.48,
      "bb_hi": 2320.82,
      "bb_recov": true,
      "bb_below": false,
      "bb_above": false,
      "bb_squeeze": false,
      "bb_near_lo": true,
      "poc_proxy": 1804.08,
      "div_bullish": false,
      "price_prev": 1568.7677001953125,
      "bb_lo_prev": 1642.89,
      "rsi_bounced_15": false,
      "rsiHistory": [
        36.82,
        34.75,
        37.65,
        32.76,
        27.91,
        26.6,
        27.74,
        29.79,
        28.01,
        27.87,
        16.31,
        14.23,
        12.6,
        8.02,
        7.82
      ],
      "rsi_direction": "subiendo",
      "promoted_by_div": false
    },
    "GOOGL": {
      "price": 368.53,
      "rsi10": 42.17,
      "rsi_prev": 44.97,
      "rsiW": 60.81,
      "ema200": 305.82,
      "emaTrend": "subiendo",
      "emaSlope": 5.654,
      "bb_lo": 361.09,
      "bb_hi": 409.66,
      "bb_recov": false,
      "bb_below": false,
      "bb_above": false,
      "bb_squeeze": false,
      "bb_near_lo": false,
      "poc_proxy": 189.97,
      "div_bullish": false,
      "price_prev": 372.19000244140625,
      "bb_lo_prev": 363.26,
      "rsi_bounced_15": false,
      "rsiHistory": [
        74.15,
        68.77,
        68.86,
        57.71,
        58.71,
        57.2,
        51.68,
        57.43,
        57.37,
        58.7,
        46.52,
        42.55,
        31.58,
        29.89,
        44.97
      ],
      "rsi_direction": "bajando",
      "promoted_by_div": false
    },
    "KO": {
      "price": 79.48,
      "rsi10": 50.86,
      "rsi_prev": 31.73,
      "rsiW": 58.92,
      "ema200": 74.57,
      "emaTrend": "subiendo",
      "emaSlope": 1.554,
      "bb_lo": 77.27,
      "bb_hi": 82.68,
      "bb_recov": true,
      "bb_below": false,
      "bb_above": false,
      "bb_squeeze": false,
      "bb_near_lo": false,
      "poc_proxy": 75.52,
      "div_bullish": false,
      "price_prev": 76.81999969482422,
      "bb_lo_prev": 77.14,
      "rsi_bounced_15": false,
      "rsiHistory": [
        70.09,
        72.09,
        74.08,
        77.45,
        72.09,
        66.82,
        68.88,
        56.13,
        64.45,
        52.83,
        42.9,
        40.65,
        39.23,
        42.62,
        31.73
      ],
      "rsi_direction": "subiendo",
      "promoted_by_div": false
    },
    "MCD": {
      "price": 279.84,
      "rsi10": 50.26,
      "rsi_prev": 31.81,
      "rsiW": 31.91,
      "ema200": 302.59,
      "emaTrend": "bajando",
      "emaSlope": -1.672,
      "bb_lo": 271.51,
      "bb_hi": 284.28,
      "bb_recov": false,
      "bb_below": false,
      "bb_above": false,
      "bb_squeeze": false,
      "bb_near_lo": false,
      "poc_proxy": 313.63,
      "div_bullish": false,
      "price_prev": 272.7200012207031,
      "bb_lo_prev": 271.26,
      "rsi_bounced_15": true,
      "rsiHistory": [
        23.47,
        28.14,
        44.3,
        41.45,
        40.54,
        49.67,
        45.85,
        40.4,
        44.45,
        39.2,
        42.35,
        36.99,
        37.7,
        32.69,
        31.81
      ],
      "rsi_direction": "subiendo",
      "promoted_by_div": false
    },
    "MELI": {
      "price": 1607.8,
      "rsi10": 38.96,
      "rsi_prev": 42.72,
      "rsiW": 36.16,
      "ema200": 1929.14,
      "emaTrend": "bajando",
      "emaSlope": -3.083,
      "bb_lo": 1531.31,
      "bb_hi": 1736.63,
      "bb_recov": false,
      "bb_below": false,
      "bb_above": false,
      "bb_squeeze": true,
      "bb_near_lo": false,
      "poc_proxy": 1778.83,
      "div_bullish": false,
      "price_prev": 1634.780029296875,
      "bb_lo_prev": 1502.66,
      "rsi_bounced_15": false,
      "rsiHistory": [
        35.91,
        31.28,
        37.1,
        38.42,
        46.34,
        49.74,
        48.03,
        45.9,
        52.74,
        52.64,
        52.66,
        57.99,
        48.08,
        43.24,
        42.72
      ],
      "rsi_direction": "bajando",
      "promoted_by_div": false
    },
    "META": {
      "price": 593.0,
      "rsi10": 39.55,
      "rsi_prev": 55.24,
      "rsiW": 41.25,
      "ema200": 642.83,
      "emaTrend": "lateral",
      "emaSlope": -0.961,
      "bb_lo": 588.04,
      "bb_hi": 637.4,
      "bb_recov": false,
      "bb_below": false,
      "bb_above": false,
      "bb_squeeze": false,
      "bb_near_lo": true,
      "poc_proxy": 604.58,
      "div_bullish": false,
      "price_prev": 627.5700073242188,
      "bb_lo_prev": 590.91,
      "rsi_bounced_15": false,
      "rsiHistory": [
        46.82,
        44.57,
        42.92,
        38.43,
        40.4,
        42.35,
        44.84,
        46.68,
        62.17,
        62.19,
        59.59,
        38.86,
        37.57,
        53.01,
        55.24
      ],
      "rsi_direction": "bajando",
      "promoted_by_div": false
    },
    "MSFT": {
      "price": 416.67,
      "rsi10": 44.61,
      "rsi_prev": 51.45,
      "rsiW": 48.1,
      "ema200": 437.25,
      "emaTrend": "lateral",
      "emaSlope": -0.658,
      "bb_lo": 395.34,
      "bb_hi": 449.82,
      "bb_recov": false,
      "bb_below": false,
      "bb_above": false,
      "bb_squeeze": false,
      "bb_near_lo": false,
      "poc_proxy": 410.29,
      "div_bullish": false,
      "price_prev": 428.04998779296875,
      "bb_lo_prev": 395.67,
      "rsi_bounced_15": false,
      "rsiHistory": [
        48.36,
        59.38,
        60.59,
        53.85,
        57.01,
        54.75,
        54.12,
        50.95,
        46.91,
        61.41,
        74.15,
        77.75,
        60.29,
        51.03,
        51.45
      ],
      "rsi_direction": "bajando",
      "promoted_by_div": false
    },
    "PEP": {
      "price": 141.92,
      "rsi10": 30.83,
      "rsi_prev": 31.36,
      "rsiW": 33.58,
      "ema200": 151.27,
      "emaTrend": "lateral",
      "emaSlope": -0.627,
      "bb_lo": 139.9,
      "bb_hi": 154.61,
      "bb_recov": false,
      "bb_below": false,
      "bb_above": false,
      "bb_squeeze": false,
      "bb_near_lo": true,
      "poc_proxy": 147.22,
      "div_bullish": false,
      "price_prev": 142.14999389648438,
      "bb_lo_prev": 140.06,
      "rsi_bounced_15": false,
      "rsiHistory": [
        34.38,
        36.16,
        36.01,
        41.69,
        38.56,
        37.29,
        45.12,
        32.35,
        40.27,
        36.89,
        32.51,
        27.83,
        29.85,
        32.21,
        31.36
      ],
      "rsi_direction": "bajando"
    },
    "QQQ": {
      "price": 705.06,
      "rsi10": 40.36,
      "rsi_prev": 72.88,
      "rsiW": 65.25,
      "ema200": 622.38,
      "emaTrend": "subiendo",
      "emaSlope": 3.505,
      "bb_lo": 693.07,
      "bb_hi": 750.95,
      "bb_recov": false,
      "bb_below": false,
      "bb_above": false,
      "bb_squeeze": true,
      "bb_near_lo": true,
      "poc_proxy": 603.51,
      "div_bullish": false,
      "price_prev": 740.6099853515625,
      "bb_lo_prev": 691.08,
      "rsi_bounced_15": false,
      "rsiHistory": [
        83.09,
        70.06,
        66.8,
        62.2,
        68.61,
        69.29,
        70.85,
        76.43,
        75.38,
        77.88,
        78.92,
        80.58,
        81.82,
        78.66,
        72.88
      ],
      "rsi_direction": "bajando",
      "promoted_by_div": false
    },
    "SPY": {
      "price": 737.55,
      "rsi10": 42.41,
      "rsi_prev": 69.24,
      "rsiW": 63.62,
      "ema200": 681.7,
      "emaTrend": "subiendo",
      "emaSlope": 2.046,
      "bb_lo": 730.13,
      "bb_hi": 762.45,
      "bb_recov": false,
      "bb_below": false,
      "bb_above": false,
      "bb_squeeze": true,
      "bb_near_lo": true,
      "poc_proxy": 682.01,
      "div_bullish": false,
      "price_prev": 757.0900268554688,
      "bb_lo_prev": 729.0,
      "rsi_bounced_15": false,
      "rsiHistory": [
        82.51,
        66.89,
        66.08,
        58.67,
        65.28,
        66.45,
        68.76,
        72.36,
        72.12,
        75.07,
        76.33,
        77.71,
        78.4,
        66.45,
        69.24
      ],
      "rsi_direction": "bajando",
      "promoted_by_div": false
    },
    "TSLA": {
      "price": 391.0,
      "rsi10": 34.67,
      "rsi_prev": 48.31,
      "rsiW": 45.97,
      "ema200": 396.05,
      "emaTrend": "subiendo",
      "emaSlope": 1.576,
      "bb_lo": 397.59,
      "bb_hi": 454.15,
      "bb_recov": false,
      "bb_below": true,
      "bb_above": false,
      "bb_squeeze": true,
      "bb_near_lo": false,
      "poc_proxy": 327.41,
      "div_bullish": false,
      "price_prev": 418.45001220703125,
      "bb_lo_prev": 402.58,
      "rsi_bounced_15": false,
      "rsiHistory": [
        72.65,
        57.29,
        50.4,
        47.36,
        54.22,
        54.51,
        58.61,
        62.14,
        65.09,
        65.85,
        60.54,
        47.2,
        51.85,
        51.83,
        48.31
      ],
      "rsi_direction": "bajando",
      "promoted_by_div": false
    },
    "V": {
      "price": 323.57,
      "rsi10": 51.26,
      "rsi_prev": 46.31,
      "rsiW": 51.07,
      "ema200": 325.36,
      "emaTrend": "lateral",
      "emaSlope": -0.034,
      "bb_lo": 314.68,
      "bb_hi": 334.58,
      "bb_recov": true,
      "bb_below": false,
      "bb_above": false,
      "bb_squeeze": false,
      "bb_near_lo": false,
      "poc_proxy": 339.85,
      "div_bullish": false,
      "price_prev": 320.17999267578125,
      "bb_lo_prev": 314.47,
      "rsi_bounced_15": false,
      "rsiHistory": [
        54.36,
        58.33,
        65.45,
        60.87,
        61.79,
        62.22,
        57.82,
        53.33,
        55.15,
        50.04,
        52.63,
        45.91,
        37.77,
        32.07,
        46.31
      ],
      "rsi_direction": "subiendo",
      "promoted_by_div": false
    },
    "WMT": {
      "price": 118.88,
      "rsi10": 41.95,
      "rsi_prev": 38.06,
      "rsiW": 44.13,
      "ema200": 116.46,
      "emaTrend": "lateral",
      "emaSlope": 1.218,
      "bb_lo": 109.6,
      "bb_hi": 138.07,
      "bb_recov": true,
      "bb_below": false,
      "bb_above": false,
      "bb_squeeze": false,
      "bb_near_lo": false,
      "poc_proxy": 108.39,
      "div_bullish": false,
      "price_prev": 117.73999786376953,
      "bb_lo_prev": 110.1,
      "rsi_bounced_15": true,
      "rsiHistory": [
        61.86,
        57.06,
        63.03,
        65.46,
        50.97,
        30.01,
        28.55,
        26.28,
        26.24,
        27.74,
        23.16,
        21.71,
        19.86,
        35.15,
        38.06
      ],
      "rsi_direction": "subiendo"
    },
    "GLD": {
      "price": 396.24,
      "rsi10": 29.41,
      "rsi_prev": 42.25,
      "rsiW": 35.35,
      "ema200": 401.25,
      "emaTrend": "lateral",
      "emaSlope": 0.774,
      "bb_lo": 397.89,
      "bb_hi": 436.66,
      "bb_recov": false,
      "bb_below": true,
      "bb_above": false,
      "bb_squeeze": false,
      "bb_near_lo": false,
      "poc_proxy": 346.1,
      "div_bullish": false,
      "price_prev": 411.2699890136719,
      "bb_lo_prev": 401.26,
      "rsi_bounced_15": false,
      "rsiHistory": [
        46.55,
        36.66,
        38.33,
        32.53,
        40.98,
        40.59,
        37.5,
        37.8,
        32.52,
        39.78,
        46.3,
        39.84,
        40.92,
        36.61,
        42.25
      ],
      "rsi_direction": "bajando",
      "promoted_by_div": false
    },
    "NU": {
      "price": 11.97,
      "rsi10": 35.25,
      "rsi_prev": 37.09,
      "rsiW": 26.27,
      "ema200": 14.67,
      "emaTrend": "bajando",
      "emaSlope": -2.791,
      "bb_lo": 11.62,
      "bb_hi": 13.84,
      "bb_recov": false,
      "bb_below": false,
      "bb_above": false,
      "bb_squeeze": true,
      "bb_near_lo": false,
      "poc_proxy": 13.39,
      "div_bullish": true,
      "price_prev": 12.119999885559082,
      "bb_lo_prev": 11.6,
      "rsi_bounced_15": false,
      "rsiHistory": [
        26.42,
        19.85,
        22.73,
        22.73,
        36.79,
        45.01,
        38.54,
        43.76,
        44.8,
        45.25,
        47.17,
        44.16,
        28.74,
        25.98,
        37.09
      ],
      "rsi_direction": "bajando",
      "promoted_by_div": false
    },
    "NVDA": {
      "price": 205.1,
      "rsi10": 39.71,
      "rsi_prev": 52.91,
      "rsiW": 54.01,
      "ema200": 186.65,
      "emaTrend": "subiendo",
      "emaSlope": 3.776,
      "bb_lo": 206.23,
      "bb_hi": 231.98,
      "bb_recov": false,
      "bb_below": true,
      "bb_above": false,
      "bb_squeeze": true,
      "bb_near_lo": false,
      "poc_proxy": 160.99,
      "div_bullish": false,
      "price_prev": 218.66000366210938,
      "bb_lo_prev": 207.69,
      "rsi_bounced_15": false,
      "rsiHistory": [
        80.85,
        64.53,
        60.61,
        58.37,
        61.05,
        55.55,
        50.24,
        49.65,
        46.71,
        49.15,
        44.84,
        60.99,
        58.77,
        48.46,
        52.91
      ],
      "rsi_direction": "bajando",
      "promoted_by_div": false
    },
    "AAPL": {
      "price": 307.34,
      "rsi10": 56.87,
      "rsi_prev": 64.54,
      "rsiW": 71.9,
      "ema200": 264.39,
      "emaTrend": "subiendo",
      "emaSlope": 3.332,
      "bb_lo": 290.64,
      "bb_hi": 317.87,
      "bb_recov": false,
      "bb_below": false,
      "bb_above": false,
      "bb_squeeze": true,
      "bb_near_lo": false,
      "poc_proxy": 224.99,
      "div_bullish": false,
      "price_prev": 311.2300109863281,
      "bb_lo_prev": 287.9,
      "rsi_bounced_15": false,
      "rsiHistory": [
        78.18,
        79.67,
        73.12,
        74.23,
        77.27,
        79.51,
        82.23,
        80.71,
        82.55,
        83.7,
        82.08,
        64.39,
        74.01,
        63.43,
        64.54
      ],
      "rsi_direction": "bajando",
      "promoted_by_div": false
    },
    "INTC": {
      "price": 99.17,
      "rsi10": 36.43,
      "rsi_prev": 50.79,
      "rsiW": 67.1,
      "ema200": 58.83,
      "emaTrend": "subiendo",
      "emaSlope": 25.095,
      "bb_lo": 101.71,
      "bb_hi": 130.09,
      "bb_recov": false,
      "bb_below": true,
      "bb_above": false,
      "bb_squeeze": false,
      "bb_near_lo": false,
      "poc_proxy": 22.21,
      "div_bullish": false,
      "price_prev": 111.77999877929688,
      "bb_lo_prev": 104.09,
      "rsi_bounced_15": false,
      "rsiHistory": [
        66.9,
        57.8,
        57.08,
        59.54,
        66.22,
        65.55,
        66.65,
        69.62,
        66.49,
        64.86,
        54.4,
        47.13,
        45.37,
        52.16,
        50.79
      ],
      "rsi_direction": "bajando",
      "promoted_by_div": false
    }
  },
  "cycles": {
    "WMT": {
      "is_silenced": true,
      "rsi_hit_50": false,
      "rsi_reset": false,
      "posicion": "completa",
      "override_sent": false
    },
    "PEP": {
      "is_silenced": true,
      "rsi_hit_50": false,
      "rsi_reset": false,
      "posicion": "media",
      "override_sent": false
    }
  },
  "daily": {
    "date": "2026-06-07",
    "signals": [],
    "watchlist": [],
    "entradas": []
  }
}